torchbiosound/__about__.py
torchbiosound/__init__.py
torchbiosound/__main__.py
torchbiosound/cli/__init__.py
torchbiosound/cli/cli.py
torchbiosound/cli/eval.py
torchbiosound/cli/learncurve.py
torchbiosound/cli/predict.py
torchbiosound/cli/prep.py
torchbiosound/cli/train.py
torchbiosound/common/__init__.py
torchbiosound/common/accelerator.py
torchbiosound/common/annotation.py
torchbiosound/common/constants.py
torchbiosound/common/converters.py
torchbiosound/common/labels.py
torchbiosound/common/learncurve.py
torchbiosound/common/logging.py
torchbiosound/common/paths.py
torchbiosound/common/tensorboard.py
torchbiosound/common/timebins.py
torchbiosound/common/timenow.py
torchbiosound/common/typing.py
torchbiosound/common/validators.py
torchbiosound/common/files/__init__.py
torchbiosound/common/files/files.py
torchbiosound/common/files/spect.py
torchbiosound/config/__init__.py
torchbiosound/config/config.py
torchbiosound/config/dataset.py
torchbiosound/config/eval.py
torchbiosound/config/learncurve.py
torchbiosound/config/load.py
torchbiosound/config/model.py
torchbiosound/config/predict.py
torchbiosound/config/prep.py
torchbiosound/config/spect_params.py
torchbiosound/config/train.py
torchbiosound/config/trainer.py
torchbiosound/config/valid-version-1.2.toml
torchbiosound/config/validators.py
torchbiosound/datapipes/__init__.py
torchbiosound/datapipes/frame_classification/__init__.py
torchbiosound/datapipes/frame_classification/constants.py
torchbiosound/datapipes/frame_classification/helper.py
torchbiosound/datapipes/frame_classification/infer_datapipe.py
torchbiosound/datapipes/frame_classification/metadata.py
torchbiosound/datapipes/frame_classification/train_datapipe.py
torchbiosound/datapipes/parametric_umap/__init__.py
torchbiosound/datapipes/parametric_umap/metadata.py
torchbiosound/datapipes/parametric_umap/parametric_umap.py
torchbiosound/datasets/__init__.py
torchbiosound/datasets/biosoundsegbench.py
torchbiosound/datasets/get.py
torchbiosound-1.0.3.dist-info/entry_points.txt
torchbiosound-1.0.3.dist-info/LICENSE
torchbiosound-1.0.3.dist-info/WHEEL
torchbiosound-1.0.3.dist-info/METADATA
torchbiosound-1.0.3.dist-info/RECORD
