Metadata-Version: 2.1
Name: torchbiosound
Version: 1.0.3
Summary: A neural network framework for researchers studying acoustic communication
Author-email: David Nicholson <nickledave@users.noreply.github.com>
Requires-Python: >=3.10
Classifier: License :: OSI Approved :: BSD License
Classifier: Development Status :: 5 - Production/Stable
Classifier: Programming Language :: Python
Classifier: Programming Language :: Python :: 3
Classifier: Programming Language :: Python :: 3.10
Classifier: Programming Language :: Python :: 3.11
Classifier: Programming Language :: Python :: 3.12
Classifier: Programming Language :: Python :: Implementation :: CPython
Requires-Dist: attrs >=23.1.0
Requires-Dist: crowsetta >=5.0.3
Requires-Dist: dask[dataframe] >=2024.5.0
Requires-Dist: evfuncs >=0.3.4
Requires-Dist: joblib >=1.4.2
Requires-Dist: lightning >=2.2.4
Requires-Dist: matplotlib >=3.7.1
Requires-Dist: numpy >=1.24.0, <2.0
Requires-Dist: pynndescent >=0.5.12
Requires-Dist: scipy >=1.9.1
Requires-Dist: SoundFile >=0.12.1
Requires-Dist: pandas >=1.4.0
Requires-Dist: tensorboard >=2.8.0
Requires-Dist: tomlkit >=0.12.4
Requires-Dist: torch >= 2.3.0
Requires-Dist: torchvision >=0.18.0
Requires-Dist: tqdm >=4.66.4
Requires-Dist: umap-learn >=0.5.6
Requires-Dist: twine >=3.3.0 ; extra == "dev"
Requires-Dist: black >=23.7.0 ; extra == "dev"
Requires-Dist: flake8 >=6.0.0 ; extra == "dev"
Requires-Dist: ipython >=7.0 ; extra == "dev"
Requires-Dist: isort >=5.12.0 ; extra == "dev"
Requires-Dist: pycln >=2.1.3 ; extra == "dev"
Requires-Dist: furo >=2022.1.2 ; extra == "doc"
Requires-Dist: myst-parser >=0.17.0 ; extra == "doc"
Requires-Dist: sphinx >=3.4.1 ; extra == "doc"
Requires-Dist: sphinxext-opengraph >=0.5.1 ; extra == "doc"
Requires-Dist: sphinx-autobuild >=2021.3.14 ; extra == "doc"
Requires-Dist: sphinx-copybutton >=0.4.0 ; extra == "doc"
Requires-Dist: sphinx-tabs >=3.4.1 ; extra == "doc"
Requires-Dist: pytest >=6.2.1 ; extra == "test"
Requires-Dist: pytest-cov >=2.11.1 ; extra == "test"
Project-URL: Documentation, https://torchbiosound.readthedocs.io
Project-URL: Source, https://github.com/biosound-org/torchbiosound
Provides-Extra: dev
Provides-Extra: doc
Provides-Extra: test
